beacon_api/__init__.py
beacon_api/__init__.pyi
beacon_api/client.py
beacon_api/client.pyi
beacon_api/dataset.py
beacon_api/dataset.pyi
beacon_api/session.py
beacon_api/session.pyi
beacon_api/table.py
beacon_api/table.pyi
beacon_api/query/__init__.py
beacon_api/query/__init__.pyi
beacon_api/query/_from.py
beacon_api/query/_from.pyi
beacon_api/query/distinct.py
beacon_api/query/distinct.pyi
beacon_api/query/filter.py
beacon_api/query/filter.pyi
beacon_api/query/functions.py
beacon_api/query/functions.pyi
beacon_api/query/node.py
beacon_api/query/node.pyi
beacon_api/query/output.py
beacon_api/query/output.pyi
beacon_api/query/select.py
beacon_api/query/select.pyi
beacon_api/query/sort.py
beacon_api/query/sort.pyi
beacon_api-1.2.1.dist-info/licenses/LICENSE
beacon_api-1.2.1.dist-info/METADATA
beacon_api-1.2.1.dist-info/WHEEL
beacon_api-1.2.1.dist-info/top_level.txt
beacon_api-1.2.1.dist-info/RECORD
