Metadata-Version: 2.4
Name: beacon-api
Version: 1.2.1
Summary: Python interface wrapper for interacting with Beacon Nodes.
Author-email: Robin Kooyman <robin@maris.nl>
License-Expression: Apache-2.0
Classifier: Programming Language :: Python :: 3
Classifier: Operating System :: OS Independent
Requires-Python: >=3.10
License-File: LICENSE
Requires-Dist: requests>=2.0.0
Requires-Dist: pandas>=2.0.0
Requires-Dist: pyarrow!=19.0.0,>=17.0.0
Requires-Dist: xarray>=2023.1.0
Requires-Dist: fsspec>=2023.1.0
Requires-Dist: dask>=2023.1.0
Requires-Dist: zarr>=2.18
Requires-Dist: networkx>=3.0.0
Requires-Dist: matplotlib>=3.0.0
Requires-Dist: netCDF4>=1.5.0
Requires-Dist: typing_extensions>=4.10.0
Requires-Dist: numpy>=1.23.0
Requires-Dist: geopandas>=1.1.0
Requires-Dist: deprecated>=1.2.14
Dynamic: license-file
